{"Nodes":[],"ExecutionTime":"2023-11-08T23:03:29.9948370Z","GenerationTime":"0001-01-01T00:00:00","PluginUserSpecFlowId":"273e3770-1db6-4b3e-9162-0ff69dcdd1ce","CLIUserSpecFlowId":null,"ExecutionResults":[{"ContextType":"Scenario","FeatureFolderPath":"Features","FeatureTitle":"This test suit contains to check Login Functionality Page","ScenarioTitle":"B. Check user is able to login page with valid username and invalid password","ScenarioArguments":["anupolavarapu19@gmail.com","Anu@1415"],"Status":"OK","StepResults":[{"Duration":"00:00:01.1304896","Status":"OK","Error":null,"Outputs":null},{"Duration":"00:00:00.0830402","Status":"OK","Error":null,"Outputs":null},{"Duration":"00:00:00.2264490","Status":"OK","Error":null,"Outputs":null},{"Duration":"00:00:03.0570503","Status":"OK","Error":null,"Outputs":null},{"Duration":"00:00:00.0324553","Status":"OK","Error":null,"Outputs":null},{"Duration":"00:00:00.0119763","Status":"OK","Error":null,"Outputs":null}],"Outputs":null}],"StepReports":null}